ussdflow/__init__.py
ussdflow/cache.py
ussdflow/models.py
ussdflow/router.py
ussdflow/utils.py
ussdflow-0.1.10.dist-info/LICENSE
ussdflow-0.1.10.dist-info/METADATA
ussdflow-0.1.10.dist-info/WHEEL
ussdflow-0.1.10.dist-info/RECORD
