Metadata-Version: 2.1
Name: ussdflow
Version: 0.1.10
Summary: 
Author: Adams Okode
Author-email: adamsokode@gmail.com
Requires-Python: >=3.10,<4.0
Classifier: Programming Language :: Python :: 3
Classifier: Programming Language :: Python :: 3.10
Classifier: Programming Language :: Python :: 3.11
Classifier: Programming Language :: Python :: 3.12
Requires-Dist: psycopg2-binary (>=2.9.9,<3.0.0)
Requires-Dist: pydantic (>=2.7.1,<3.0.0)
Requires-Dist: redis (>=5.0.4,<6.0.0)
Requires-Dist: sqlalchemy (>=2.0.30,<3.0.0)
